deconvolawrence/__init__.py
deconvolawrence/baf2sql.py
deconvolawrence/baf2sql2unidec.py
deconvolawrence/baf2sql_c.dll
deconvolawrence/meta_processing.py
deconvolawrence/ms_plotter_tools.py
deconvolawrence-0.3.2.dist-info/LICENSE
deconvolawrence-0.3.2.dist-info/METADATA
deconvolawrence-0.3.2.dist-info/WHEEL
deconvolawrence-0.3.2.dist-info/top_level.txt
deconvolawrence-0.3.2.dist-info/RECORD
