Metadata-Version: 2.1
Name: deconvolawrence
Version: 0.3.2
Summary: Automated deconvolution of mass spectra datasets
Home-page: https://github.com/lawrencecollins/deconvolawrence
Author: Lawrence Collins
Author-email: cm19ljc@leeds.ac.uk
Classifier: Programming Language :: Python :: 3
Classifier: License :: OSI Approved :: MIT License
Classifier: Operating System :: OS Independent
Requires-Python: >=3.6
License-File: LICENSE
Requires-Dist: unidec
Requires-Dist: seaborn
